kdependencies/__init__.py
kdependencies/dependencies.py
kdependencies/models/__init__.py
kdependencies/models/installed_package.py
kdependencies/models/package.py
kdependencies/models/core/__init__.py
kdependencies/models/core/utils.py
kdependencies-0.0.4.dist-info/METADATA
kdependencies-0.0.4.dist-info/WHEEL
kdependencies-0.0.4.dist-info/top_level.txt
kdependencies-0.0.4.dist-info/RECORD
